pyorbx.py
pyorbx-0.2.0.dist-info/METADATA
pyorbx-0.2.0.dist-info/WHEEL
pyorbx-0.2.0.dist-info/top_level.txt
pyorbx-0.2.0.dist-info/RECORD
