Metadata-Version: 2.4
Name: pyorbx
Version: 0.2.0
Summary: Cinematic legacy module with branded aliases and procedural clarity.
Author: Anonymous
Author-email: anon@legacy.dev
Classifier: Programming Language :: Python :: 3
Classifier: License :: OSI Approved :: MIT License
Classifier: Operating System :: OS Independent
Requires-Python: >=3.6
Dynamic: author
Dynamic: author-email
Dynamic: classifier
Dynamic: requires-python
Dynamic: summary
